odoo8_addon_crm_sector-8.0.1.0.0.99.dev17-py3.8-nspkg.pth
odoo_addons/crm_sector/README.rst
odoo_addons/crm_sector/__init__.py
odoo_addons/crm_sector/__openerp__.py
odoo_addons/crm_sector/i18n/.gitkeep
odoo_addons/crm_sector/i18n/bg.po
odoo_addons/crm_sector/i18n/crm_sector.pot
odoo_addons/crm_sector/i18n/de.po
odoo_addons/crm_sector/i18n/es.po
odoo_addons/crm_sector/i18n/fr.po
odoo_addons/crm_sector/i18n/hr.po
odoo_addons/crm_sector/i18n/it.po
odoo_addons/crm_sector/i18n/nb.po
odoo_addons/crm_sector/i18n/pt_BR.po
odoo_addons/crm_sector/i18n/sk.po
odoo_addons/crm_sector/i18n/sl.po
odoo_addons/crm_sector/i18n/sv.po
odoo_addons/crm_sector/i18n/tr.po
odoo_addons/crm_sector/i18n/tr_TR.po
odoo_addons/crm_sector/i18n/zh_CN.po
odoo_addons/crm_sector/models/__init__.py
odoo_addons/crm_sector/models/crm_lead.py
odoo_addons/crm_sector/static/description/icon.png
odoo_addons/crm_sector/tests/__init__.py
odoo_addons/crm_sector/tests/test_crm_lead.py
odoo_addons/crm_sector/views/crm_lead_view.xml
odoo8_addon_crm_sector-8.0.1.0.0.99.dev17.dist-info/METADATA
odoo8_addon_crm_sector-8.0.1.0.0.99.dev17.dist-info/WHEEL
odoo8_addon_crm_sector-8.0.1.0.0.99.dev17.dist-info/namespace_packages.txt
odoo8_addon_crm_sector-8.0.1.0.0.99.dev17.dist-info/top_level.txt
odoo8_addon_crm_sector-8.0.1.0.0.99.dev17.dist-info/RECORD
